WannierOwl/__init__.py
WannierOwl-0.0.0.dist-info/LICENSE
WannierOwl-0.0.0.dist-info/METADATA
WannierOwl-0.0.0.dist-info/WHEEL
WannierOwl-0.0.0.dist-info/top_level.txt
WannierOwl-0.0.0.dist-info/RECORD
